spi_repl/__main__.py
spi_repl/spi.py
spi_repl-0.1.3.dist-info/LICENSE
spi_repl-0.1.3.dist-info/METADATA
spi_repl-0.1.3.dist-info/WHEEL
spi_repl-0.1.3.dist-info/entry_points.txt
spi_repl-0.1.3.dist-info/RECORD
